taskotron_python_versions/__init__.py
taskotron_python_versions/common.py
taskotron_python_versions/executables.py
taskotron_python_versions/naming_scheme.py
taskotron_python_versions/py3_support.py
taskotron_python_versions/python_usage.py
taskotron_python_versions/python_usage_obsoleted.py
taskotron_python_versions/requires.py
taskotron_python_versions/two_three.py
taskotron_python_versions/unversioned_shebangs.py
taskotron_python_versions-0.1.dev6.dist-info/LICENSE
taskotron_python_versions-0.1.dev6.dist-info/METADATA
taskotron_python_versions-0.1.dev6.dist-info/WHEEL
taskotron_python_versions-0.1.dev6.dist-info/top_level.txt
taskotron_python_versions-0.1.dev6.dist-info/RECORD
