Metadata-Version: 2.1
Name: taskotron-python-versions
Version: 0.1.dev6
Summary: Taskotron checks regarding Python versions
Home-page: https://github.com/fedora-python/taskotron-python-versions
Author: Miro Hrončok, Iryna Shcherbina, Michal Cyprian
Author-email: mhroncok@redhat.com, ishcherb@redhat.com, mcyprian@redhat.com
License: Public Domain
Keywords: taskotron fedora python rpm
Platform: UNKNOWN
Classifier: Development Status :: 4 - Beta
Classifier: Intended Audience :: Developers
Classifier: License :: CC0 1.0 Universal (CC0 1.0) Public Domain Dedication
Classifier: Operating System :: POSIX :: Linux
Classifier: Programming Language :: Python
Classifier: Programming Language :: Python :: 3
Classifier: Topic :: Software Development :: Testing
Requires-Dist: libarchive-c
Requires-Dist: python-bugzilla
